devqubit_qiskit_runtime/__init__.py
devqubit_qiskit_runtime/adapter.py
devqubit_qiskit_runtime/circuits.py
devqubit_qiskit_runtime/device.py
devqubit_qiskit_runtime/pubs.py
devqubit_qiskit_runtime/py.typed
devqubit_qiskit_runtime/results.py
devqubit_qiskit_runtime/transpilation.py
devqubit_qiskit_runtime/utils.py
devqubit_qiskit_runtime-0.1.10.dist-info/METADATA
devqubit_qiskit_runtime-0.1.10.dist-info/WHEEL
devqubit_qiskit_runtime-0.1.10.dist-info/entry_points.txt
devqubit_qiskit_runtime-0.1.10.dist-info/licenses/LICENSE
devqubit_qiskit_runtime-0.1.10.dist-info/RECORD
