Metadata-Version: 2.4
Name: devqubit-qiskit-runtime
Version: 0.1.10
Summary: devqubit adapter for Qiskit Runtime
License-File: LICENSE
Requires-Python: <3.14,>=3.11
Requires-Dist: devqubit-engine<0.2.0,>=0.1.10
Requires-Dist: devqubit-qiskit<0.2.0,>=0.1.10
Requires-Dist: qiskit-ibm-runtime<0.45,>=0.44
